.coveragerc
.travis.yml
AUTHORS
AUTHORS.rst
ChangeLog
LICENSE
README.rst
setup.cfg
setup.py
tox.ini
deuce_client.egg-info/PKG-INFO
deuce_client.egg-info/SOURCES.txt
deuce_client.egg-info/dependency_links.txt
deuce_client.egg-info/entry_points.txt
deuce_client.egg-info/not-zip-safe
deuce_client.egg-info/pbr.json
deuce_client.egg-info/requires.txt
deuce_client.egg-info/top_level.txt
deuceclient/__init__.py
deuceclient/shell.py
deuceclient/api/__init__.py
deuceclient/api/afile.py
deuceclient/api/block.py
deuceclient/api/blocks.py
deuceclient/api/files.py
deuceclient/api/project.py
deuceclient/api/splitter.py
deuceclient/api/storageblocks.py
deuceclient/api/v1.py
deuceclient/api/vault.py
deuceclient/auth/__init__.py
deuceclient/auth/base.py
deuceclient/auth/nonauth.py
deuceclient/auth/openstackauth.py
deuceclient/auth/rackspaceauth.py
deuceclient/client/__init__.py
deuceclient/client/deuce.py
deuceclient/common/__init__.py
deuceclient/common/command.py
deuceclient/common/errors.py
deuceclient/common/validation.py
deuceclient/common/validation_instance.py
deuceclient/tests/__init__.py
deuceclient/tests/test_api_block.py
deuceclient/tests/test_api_blocks.py
deuceclient/tests/test_api_file.py
deuceclient/tests/test_api_files.py
deuceclient/tests/test_api_project.py
deuceclient/tests/test_api_storage_blocks.py
deuceclient/tests/test_api_v1.py
deuceclient/tests/test_api_vault.py
deuceclient/tests/test_api_vault_serialize.py
deuceclient/tests/test_auth.py
deuceclient/tests/test_auth_noauth.py
deuceclient/tests/test_auth_openstack.py
deuceclient/tests/test_auth_rackspace.py
deuceclient/tests/test_client_deuce.py
deuceclient/tests/test_client_deuce_block.py
deuceclient/tests/test_client_deuce_file_blocks_assign.py
deuceclient/tests/test_client_deuce_file_blocks_get.py
deuceclient/tests/test_client_deuce_file_creation.py
deuceclient/tests/test_client_deuce_file_deletion.py
deuceclient/tests/test_client_deuce_file_download.py
deuceclient/tests/test_client_deuce_file_files_get.py
deuceclient/tests/test_client_deuce_file_finalize.py
deuceclient/tests/test_client_deuce_init.py
deuceclient/tests/test_client_deuce_storage_block.py
deuceclient/tests/test_client_deuce_vault.py
deuceclient/tests/test_common_command.py
deuceclient/tests/test_common_validation.py
